deepcov/__init__.py
deepcov/cli.py
deepcov/pytest_plugin.py
pytest_deepcov-0.0.9.dist-info/entry_points.txt
pytest_deepcov-0.0.9.dist-info/WHEEL
pytest_deepcov-0.0.9.dist-info/METADATA
pytest_deepcov-0.0.9.dist-info/RECORD
