Metadata-Version: 2.1
Name: pytest-deepcov
Version: 0.0.9
Summary: deepcov
Home-page: https://github.com/treebeardtech/deepcov
License: Apache-2.0
Author: alex-treebeard
Author-email: alex@treebeard.io
Requires-Python: >=3.8,<4.0
Classifier: License :: OSI Approved :: Apache Software License
Classifier: Programming Language :: Python :: 3
Classifier: Programming Language :: Python :: 3.8
Classifier: Programming Language :: Python :: 3.9
Requires-Dist: click (>=7.1.2,<8.0.0)
Requires-Dist: coverage (>=5.5,<6.0)
Requires-Dist: junitparser (>=2.0.0,<3.0.0)
Requires-Dist: pydantic (>=1.8.1,<2.0.0)
Requires-Dist: pytest-cov (>=2.11.1,<3.0.0)
Requires-Dist: rich (>=9.13.0,<10.0.0)
Requires-Dist: timeago (>=1.0.15,<2.0.0)
